model_values/__init__.py
model_values/py.typed
django_model_values-1.6.dist-info/LICENSE.txt
django_model_values-1.6.dist-info/METADATA
django_model_values-1.6.dist-info/WHEEL
django_model_values-1.6.dist-info/top_level.txt
django_model_values-1.6.dist-info/RECORD
