Metadata-Version: 2.1
Name: django-model-values
Version: 1.6
Summary: Taking the O out of ORM.
Author-email: Aric Coady <aric.coady@gmail.com>
License: Copyright 2022 Aric Coady
Project-URL: Homepage, https://github.com/coady/django-model-values
Project-URL: Documentation, https://coady.github.io/django-model-values
Project-URL: Changelog, https://github.com/coady/django-model-values/blob/main/CHANGELOG.md
Project-URL: Issues, https://github.com/coady/django-model-values/issues
Keywords: values_list,pandas,column-oriented,data,mapper,pattern,orm
Classifier: Development Status :: 6 - Mature
Classifier: Framework :: Django :: 4
Classifier: Framework :: Django :: 4.2
Classifier: Framework :: Django :: 5.0
Classifier: Intended Audience :: Developers
Classifier: License :: OSI Approved :: Apache Software License
Classifier: Operating System :: OS Independent
Classifier: Programming Language :: Python :: 3
Classifier: Programming Language :: Python :: 3.8
Classifier: Programming Language :: Python :: 3.9
Classifier: Programming Language :: Python :: 3.10
Classifier: Programming Language :: Python :: 3.11
Classifier: Programming Language :: Python :: 3.12
Classifier: Topic :: Database :: Database Engines/Servers
Classifier: Topic :: Software Development :: Libraries :: Python Modules
Classifier: Typing :: Typed
Requires-Python: >=3.8
License-File: LICENSE.txt
Requires-Dist: django >=4.2
